wield/iirrational/__init__.py
wield/iirrational/_version.py
wield/iirrational/data2testcase.py
wield/iirrational/setup.py
wield/iirrational/svd.py
wield/iirrational/version.py
wield/iirrational/LIGO/__init__.py
wield/iirrational/LIGO/conversion.py
wield/iirrational/LIGO/noise_model.py
wield/iirrational/TFmath/TF.py
wield/iirrational/TFmath/__init__.py
wield/iirrational/TFmath/analytic_functionals.py
wield/iirrational/TFmath/order_reduce.py
wield/iirrational/TFmath/roots_bin.py
wield/iirrational/TFmath/roots_matching.py
wield/iirrational/TFmath/setup.py
wield/iirrational/TFmath/statespace.py
wield/iirrational/TFmath/lapack/__init__.py
wield/iirrational/TFmath/lapack/setup.py
wield/iirrational/TFmath/lapack/svd.py
wield/iirrational/annotate/__init__.py
wield/iirrational/annotate/annotate.py
wield/iirrational/annotate/exporters.py
wield/iirrational/annotate/markdown.py
wield/iirrational/external/__init__.py
wield/iirrational/external/scipy_optimize/__init__.py
wield/iirrational/external/scipy_optimize/common.py
wield/iirrational/external/scipy_optimize/neldermead.py
wield/iirrational/external/scipy_optimize/trf.py
wield/iirrational/external/tabulate/__init__.py
wield/iirrational/external/tabulate/tabulate.py
wield/iirrational/file_io/__init__.py
wield/iirrational/file_io/any_io.py
wield/iirrational/file_io/csv_io.py
wield/iirrational/file_io/hdf5_io.py
wield/iirrational/file_io/ini_io.py
wield/iirrational/file_io/json_io.py
wield/iirrational/file_io/matlab_io.py
wield/iirrational/file_io/pickle_io.py
wield/iirrational/file_io/types.py
wield/iirrational/file_io/utilities.py
wield/iirrational/file_io/yaml_io.py
wield/iirrational/fitters_ZPK/MRF.py
wield/iirrational/fitters_ZPK/ZPKrep2MRF.py
wield/iirrational/fitters_ZPK/__init__.py
wield/iirrational/fitters_ZPK/data_filtfit_base.py
wield/iirrational/fitters_ZPK/mappings.py
wield/iirrational/fitters_ZPK/codings_cmn/__init__.py
wield/iirrational/fitters_ZPK/codings_cmn/base.py
wield.iirrational-2.9.5.dist-info/Apache-2.0.txt
wield.iirrational-2.9.5.dist-info/CC0-1.0.txt
wield.iirrational-2.9.5.dist-info/METADATA
wield.iirrational-2.9.5.dist-info/NOTICE
wield.iirrational-2.9.5.dist-info/WHEEL
wield.iirrational-2.9.5.dist-info/top_level.txt
wield.iirrational-2.9.5.dist-info/RECORD
